hazyhorizon/__init__.py
hazyhorizon/main.py
hazyhorizon/metrics.py
hazyhorizon-0.1.0.dist-info/METADATA
hazyhorizon-0.1.0.dist-info/WHEEL
hazyhorizon-0.1.0.dist-info/licenses/LICENSE
hazyhorizon-0.1.0.dist-info/RECORD
