Metadata-Version: 2.4
Name: hazyhorizon
Version: 0.1.0
Summary: Non-paradigmatic support for time series processing and forecasting
Project-URL: Homepage, https://github.com/Pawel-Kranzberg/hazyhorizon
Project-URL: Repository, https://github.com/Pawel-Kranzberg/hazyhorizon
Project-URL: Issues, https://github.com/Pawel-Kranzberg/hazyhorizon/issues
Author-email: Paweł Kranzberg <pawel.kranzberg@gmail.com>
License: Apache-2.0
License-File: LICENSE
Keywords: data-science,forecasting,machine-learning,time-series
Classifier: Development Status :: 3 - Alpha
Classifier: Intended Audience :: Developers
Classifier: Intended Audience :: Science/Research
Classifier: License :: OSI Approved :: Apache Software License
Classifier: Operating System :: OS Independent
Classifier: Programming Language :: Python :: 3
Classifier: Programming Language :: Python :: 3.11
Classifier: Programming Language :: Python :: 3.12
Classifier: Topic :: Scientific/Engineering
Classifier: Topic :: Software Development :: Libraries :: Python Modules
Requires-Python: >=3.11
Requires-Dist: scikit-learn<2,>=1.6.1
Requires-Dist: scipy<2,>=1.15.2
